clonevirtualenv.py
virtualenv_clone-0.5.3.dist-info/LICENSE
virtualenv_clone-0.5.3.dist-info/METADATA
virtualenv_clone-0.5.3.dist-info/WHEEL
virtualenv_clone-0.5.3.dist-info/entry_points.txt
virtualenv_clone-0.5.3.dist-info/top_level.txt
virtualenv_clone-0.5.3.dist-info/RECORD
